setup.py
datadb/__init__.py
datadb.egg-info/PKG-INFO
datadb.egg-info/SOURCES.txt
datadb.egg-info/dependency_links.txt
datadb.egg-info/requires.txt
datadb.egg-info/top_level.txt
datadb/minidb/__init__.py
datadb/minidb/mdb.py
datadb/minidb/building_blocks/__init__.py
datadb/minidb/building_blocks/base/__init__.py
datadb/minidb/building_blocks/base/barchart.py
datadb/minidb/building_blocks/base/boxplot.py
datadb/minidb/building_blocks/base/describe_table.py
datadb/minidb/building_blocks/base/histogram.py
datadb/minidb/building_blocks/base/value_counts_table.py
datadb/minidb/building_blocks/date/__init__.py
datadb/minidb/building_blocks/date/timeplot.py
datadb/minidb/building_blocks/date/timeplot_categorical.py
datadb/minidb/building_blocks/target/__init__.py
datadb/minidb/building_blocks/target/target_info.py
datadb/minidb/mini_dashboards/__init__.py
datadb/minidb/mini_dashboards/minidashboard_base.py
datadb/minidb/mini_dashboards/minidashboard_target.py
datadb/minidb/mini_dashboards/minidashboard_time.py