Metadata-Version: 2.1
Name: datadb
Version: 0.0.6
Summary: tool to assess data
Author: Rens Jochemsen
Author-email: rensjochemsen@gmail.com
License: MIT
Platform: UNKNOWN
Classifier: Programming Language :: Python :: 3
Classifier: Operating System :: Microsoft :: Windows
